freellama/__init__.py
freellama/__main__.py
freellama/core.py
freellama-1.0.1.dist-info/licenses/LICENSE
freellama-1.0.1.dist-info/METADATA
freellama-1.0.1.dist-info/WHEEL
freellama-1.0.1.dist-info/entry_points.txt
freellama-1.0.1.dist-info/top_level.txt
freellama-1.0.1.dist-info/RECORD
