Metadata-Version: 2.4
Name: freellama
Version: 1.0.1
Summary: The simplest way to chat with Llama-3.3-70B for free
Home-page: https://github.com/IMApurbo/freellama
Author: AKM Korishee Apurbo
Author-email: bandinvisible8@gmail.com
License: MIT
Keywords: llm ai chatbot llama free groq
Classifier: Programming Language :: Python :: 3
Classifier: License :: OSI Approved :: MIT License
Classifier: Operating System :: OS Independent
Classifier: Topic :: Scientific/Engineering :: Artificial Intelligence
Requires-Python: >=3.8
License-File: LICENSE
Requires-Dist: requests>=2.25.0
Dynamic: author
Dynamic: author-email
Dynamic: classifier
Dynamic: description
Dynamic: description-content-type
Dynamic: home-page
Dynamic: keywords
Dynamic: license
Dynamic: license-file
Dynamic: requires-dist
Dynamic: requires-python
Dynamic: summary
